{"lastUsed":1730735869140,"path":"D:\/AlejandroFH\/Desarrollo de Interfaces\/Repositorio DI\/DI_CalculadoraFinanzas","projectCount":2,"recentFiles":[{"path":"\/CalculadoraFinanzas","parentWorkspace":"D:\/AlejandroFH\/Desarrollo de Interfaces\/Repositorio DI\/DI_CalculadoraFinanzas","name":".gitignore","lastModified":1730735869140,"locationURI":"file:\/D:\/AlejandroFH\/Desarrollo%20de%20Interfaces\/Repositorio%20DI\/DI_CalculadoraFinanzas\/CalculadoraFinanzas\/.gitignore"},{"path":"\/CalculadoraFinanzas\/src\/application","parentWorkspace":"D:\/AlejandroFH\/Desarrollo de Interfaces\/Repositorio DI\/DI_CalculadoraFinanzas","name":"Main.java","lastModified":1730734510775,"locationURI":"file:\/D:\/AlejandroFH\/Desarrollo%20de%20Interfaces\/Repositorio%20DI\/DI_CalculadoraFinanzas\/CalculadoraFinanzas\/src\/application\/Main.java"}]}